fringes/__init__.py
fringes/__main__.py
fringes/decoder.py
fringes/decoder_numba.py
fringes/filter.py
fringes/fringes.py
fringes/grid.py
fringes/util.py
fringes-2.0.0.dist-info/licenses/LICENSE.txt
fringes-2.0.0.dist-info/METADATA
fringes-2.0.0.dist-info/WHEEL
fringes-2.0.0.dist-info/entry_points.txt
fringes-2.0.0.dist-info/top_level.txt
fringes-2.0.0.dist-info/RECORD
