Metadata-Version: 2.4
Name: Fringes
Version: 2.0.0
Summary: Phase shifting algorithms for encoding and decoding sinusoidal fringe patterns.
Author: Christian Kludt
License-Expression: GPL-3.0-only
Project-URL: Documentation, https://fringes.readthedocs.io
Project-URL: Repository, https://github.com/comimag/fringes
Project-URL: Donate, https://www.paypal.com/cgi-bin/webscr?cmd=_s-xclick&hosted_button_id=EHBGZ229DKUC4
Keywords: phase shifting,phase unwrapping,fringe analysis,fringe projection,deflectometry,computational imaging
Classifier: Topic :: Scientific/Engineering :: Image Processing
Classifier: Intended Audience :: Education
Classifier: Intended Audience :: Science/Research
Requires-Python: >=3.10
License-File: LICENSE.txt
Requires-Dist: numba>=0.55
Requires-Dist: numpy>=1.21.2
Requires-Dist: opencv-contrib-python>=4.5.4.58
Requires-Dist: pyyaml>=6.0.2
Requires-Dist: scikit-image>=0.19
Requires-Dist: scipy>=1.7
Requires-Dist: sympy>=1.13.3
Dynamic: license-file
